{
  "_class": "shapePath",
  "booleanOperation": -1,
  "do_objectID": "57AB5D76-9340-4BE6-886B-6D3EDB9D7041",
  "edited": true,
  "exportOptions": {
    "_class": "exportOptions",
    "exportFormats": [
    ],
    "includedLayerIds": [
    ],
    "layerOptions": 0,
    "shouldTrim": false
  },
  "frame": {
    "_class": "rect",
    "constrainProportions": false,
    "height": 12,
    "width": 12,
    "x": 0,
    "y": 0
  },
  "isFlippedHorizontal": false,
  "isFlippedVertical": false,
  "isLocked": false,
  "isVisible": true,
  "layerListExpandedType": 0,
  "name": "add-contact-path",
  "nameIsFixed": false,
  "path": {
    "_class": "path",
    "isClosed": true,
    "pointRadiusBehaviour": 0,
    "points": [
      {
        "_class": "curvePoint",
        "cornerRadius": 0,
        "curveFrom": "{0.45454545454545453, 0.53333333333333333}",
        "curveMode": 1,
        "curveTo": "{0.45454545454545453, 0.53333333333333333}",
        "hasCurveFrom": false,
        "hasCurveTo": false,
        "point": "{0.45454545454545453, 0.53333333333333333}"
      },
      {
        "_class": "curvePoint",
        "cornerRadius": 0,
        "curveFrom": "{0, 0.53333333333333333}",
        "curveMode": 1,
        "curveTo": "{0, 0.53333333333333333}",
        "hasCurveFrom": false,
        "hasCurveTo": false,
        "point": "{0, 0.53333333333333333}"
      },
      {
        "_class": "curvePoint",
        "cornerRadius": 0,
        "curveFrom": "{0, 0.46666666666666667}",
        "curveMode": 1,
        "curveTo": "{0, 0.46666666666666667}",
        "hasCurveFrom": false,
        "hasCurveTo": false,
        "point": "{0, 0.46666666666666667}"
      },
      {
        "_class": "curvePoint",
        "cornerRadius": 0,
        "curveFrom": "{0.45454545454545453, 0.46666666666666667}",
        "curveMode": 1,
        "curveTo": "{0.45454545454545453, 0.46666666666666667}",
        "hasCurveFrom": false,
        "hasCurveTo": false,
        "point": "{0.45454545454545453, 0.46666666666666667}"
      },
      {
        "_class": "curvePoint",
        "cornerRadius": 0,
        "curveFrom": "{0.45454545454545453, 0}",
        "curveMode": 1,
        "curveTo": "{0.45454545454545453, 0}",
        "hasCurveFrom": false,
        "hasCurveTo": false,
        "point": "{0.45454545454545453, 0}"
      },
      {
        "_class": "curvePoint",
        "cornerRadius": 0,
        "curveFrom": "{0.52272727272727271, 0}",
        "curveMode": 1,
        "curveTo": "{0.52272727272727271, 0}",
        "hasCurveFrom": false,
        "hasCurveTo": false,
        "point": "{0.52272727272727271, 0}"
      },
      {
        "_class": "curvePoint",
        "cornerRadius": 0,
        "curveFrom": "{0.52272727272727271, 0.46666666666666667}",
        "curveMode": 1,
        "curveTo": "{0.52272727272727271, 0.46666666666666667}",
        "hasCurveFrom": false,
        "hasCurveTo": false,
        "point": "{0.52272727272727271, 0.46666666666666667}"
      },
      {
        "_class": "curvePoint",
        "cornerRadius": 0,
        "curveFrom": "{1, 0.46666666666666667}",
        "curveMode": 1,
        "curveTo": "{1, 0.46666666666666667}",
        "hasCurveFrom": false,
        "hasCurveTo": false,
        "point": "{1, 0.46666666666666667}"
      },
      {
        "_class": "curvePoint",
        "cornerRadius": 0,
        "curveFrom": "{1, 0.53333333333333333}",
        "curveMode": 1,
        "curveTo": "{1, 0.53333333333333333}",
        "hasCurveFrom": false,
        "hasCurveTo": false,
        "point": "{1, 0.53333333333333333}"
      },
      {
        "_class": "curvePoint",
        "cornerRadius": 0,
        "curveFrom": "{0.52272727272727271, 0.53333333333333333}",
        "curveMode": 1,
        "curveTo": "{0.52272727272727271, 0.53333333333333333}",
        "hasCurveFrom": false,
        "hasCurveTo": false,
        "point": "{0.52272727272727271, 0.53333333333333333}"
      },
      {
        "_class": "curvePoint",
        "cornerRadius": 0,
        "curveFrom": "{0.52272727272727271, 1}",
        "curveMode": 1,
        "curveTo": "{0.52272727272727271, 1}",
        "hasCurveFrom": false,
        "hasCurveTo": false,
        "point": "{0.52272727272727271, 1}"
      },
      {
        "_class": "curvePoint",
        "cornerRadius": 0,
        "curveFrom": "{0.45454545454545453, 1}",
        "curveMode": 1,
        "curveTo": "{0.45454545454545453, 1}",
        "hasCurveFrom": false,
        "hasCurveTo": false,
        "point": "{0.45454545454545453, 1}"
      },
      {
        "_class": "curvePoint",
        "cornerRadius": 0,
        "curveFrom": "{0.45454545454545453, 0.53333333333333333}",
        "curveMode": 1,
        "curveTo": "{0.45454545454545453, 0.53333333333333333}",
        "hasCurveFrom": false,
        "hasCurveTo": false,
        "point": "{0.45454545454545453, 0.53333333333333333}"
      }
    ]
  },
  "resizingConstraint": 63,
  "resizingType": 0,
  "rotation": 0,
  "shouldBreakMaskChain": false
}